{
  "generated_at": "2026-04-25T11:14:23+00:00",
  "source_check": [
    "https://www.zdfheute.de/panorama/wal-timmy-ostsee-liveblog-100.html",
    "https://www.deutsches-meeresmuseum.de/wissenschaft/sichtungen/buckelwal-in-der-ostsee",
    "https://www.nordkurier.de/suche?q=timmy+wal"
  ],
  "entries": [
    {
      "source": "ZDFheute Liveblog",
      "title": "Rettungsrinne soll heute fertig werden",
      "url": "https://www.zdfheute.de/panorama/wal-timmy-ostsee-liveblog-100.html",
      "timestamp": "2026-04-25T11:14:20+00:00",
      "id": "2a83adb8181b"
    },
    {
      "source": "ZDFheute Liveblog",
      "title": "Sandsäcke zum Wal gebracht",
      "url": "https://www.zdfheute.de/panorama/wal-timmy-ostsee-liveblog-100.html",
      "timestamp": "2026-04-25T10:13:36+00:00",
      "id": "832e58fe70a4"
    },
    {
      "source": "ZDFheute Liveblog",
      "title": "\"Deutschlands Lieblingswal\": Wie im Ausland berichtet wird",
      "url": "https://www.zdfheute.de/panorama/wal-timmy-ostsee-liveblog-100.html",
      "timestamp": "2026-04-25T09:16:59+00:00",
      "id": "1493684d8b64"
    },
    {
      "source": "ZDFheute Liveblog",
      "title": "Der Wal verharrt weiter vor Poel",
      "url": "https://www.zdfheute.de/panorama/wal-timmy-ostsee-liveblog-100.html",
      "timestamp": "2026-04-25T08:17:23+00:00",
      "id": "0d3cd88d5bf9"
    },
    {
      "source": "ZDFheute Liveblog",
      "title": "Möglicherweise neuer Rettungsversuch am Wochenende",
      "url": "https://www.zdfheute.de/panorama/wal-timmy-ostsee-liveblog-100.html",
      "timestamp": "2026-04-24T21:15:11+00:00",
      "id": "7012cacd046c"
    },
    {
      "source": "ZDFheute Liveblog",
      "title": "Backhaus: Zeitfenster für Rettung beginnt, sich zu schließen",
      "url": "https://www.zdfheute.de/panorama/wal-timmy-ostsee-liveblog-100.html",
      "timestamp": "2026-04-24T15:24:37+00:00",
      "id": "919f1d53aef3"
    },
    {
      "source": "ZDFheute Liveblog",
      "title": "19 Eilanträge zum Wal beim Verwaltungsgericht",
      "url": "https://www.zdfheute.de/panorama/wal-timmy-ostsee-liveblog-100.html",
      "timestamp": "2026-04-24T15:24:37+00:00",
      "id": "7059bb4187f3"
    },
    {
      "source": "ZDFheute Liveblog",
      "title": "Umweltministerium prüft neuen Rettungsplan",
      "url": "https://www.zdfheute.de/panorama/wal-timmy-ostsee-liveblog-100.html",
      "timestamp": "2026-04-24T13:30:11+00:00",
      "id": "2800c68ec7fa"
    },
    {
      "source": "ZDFheute Liveblog",
      "title": "Geldgeber Gunz will weiter Wal-Transport \"bis zum Ende\"",
      "url": "https://www.zdfheute.de/panorama/wal-timmy-ostsee-liveblog-100.html",
      "timestamp": "2026-04-24T12:16:29+00:00",
      "id": "28df4fa4a35e"
    },
    {
      "source": "ZDFheute Liveblog",
      "title": "Geschwächter Buckelwal: Rettung weiter offen",
      "url": "https://www.zdfheute.de/panorama/wal-timmy-ostsee-liveblog-100.html",
      "timestamp": "2026-04-24T11:23:39+00:00",
      "id": "9bbb01fa3a34"
    },
    {
      "source": "ZDFheute Liveblog",
      "title": "Planungen für die Wal-Rettung laufen weiter",
      "url": "https://www.zdfheute.de/panorama/wal-timmy-ostsee-liveblog-100.html",
      "timestamp": "2026-04-24T06:34:51+00:00",
      "id": "1adef39b70c0"
    },
    {
      "source": "ZDFheute Liveblog",
      "title": "Wal liegt weiter im flachen Wasser",
      "url": "https://www.zdfheute.de/panorama/wal-timmy-ostsee-liveblog-100.html",
      "timestamp": "2026-04-23T19:37:36+00:00",
      "id": "a4f53a30daa9"
    },
    {
      "source": "Dt. Meeresmuseum",
      "title": "„Forschungsstiftung Ostsee“ vergibt Preise an herausragende Nachwuchswissenschaftler*innen",
      "url": "https://www.deutsches-meeresmuseum.de/wissenschaft/sichtungen/buckelwal-in-der-ostsee",
      "timestamp": "2026-04-23T17:55:51+00:00",
      "id": "266fcd7441b1"
    },
    {
      "source": "ZDFheute Liveblog",
      "title": "Ministerium wartet auf neues Wal-Rettungskonzept",
      "url": "https://www.zdfheute.de/panorama/wal-timmy-ostsee-liveblog-100.html",
      "timestamp": "2026-04-23T17:55:50+00:00",
      "id": "e4a04ae15036"
    },
    {
      "source": "ZDFheute Liveblog",
      "title": "Mindestens fünf Helfer beim Wal",
      "url": "https://www.zdfheute.de/panorama/wal-timmy-ostsee-liveblog-100.html",
      "timestamp": "2026-04-23T17:55:50+00:00",
      "id": "29059d634216"
    },
    {
      "source": "ZDFheute Liveblog",
      "title": "Neuer Rettungsplan: \"110 Meter lange Furche\"",
      "url": "https://www.zdfheute.de/panorama/wal-timmy-ostsee-liveblog-100.html",
      "timestamp": "2026-04-23T17:55:50+00:00",
      "id": "7123a6780cf5"
    },
    {
      "source": "ZDFheute Liveblog",
      "title": "Viel Trubel wegen Wal: \"Die Leute hier sind genervt\"",
      "url": "https://www.zdfheute.de/panorama/wal-timmy-ostsee-liveblog-100.html",
      "timestamp": "2026-04-23T17:55:50+00:00",
      "id": "8cc6144a7375"
    },
    {
      "source": "ZDFheute Liveblog",
      "title": "Rettungsteam will auf Lastkahn setzen",
      "url": "https://www.zdfheute.de/panorama/wal-timmy-ostsee-liveblog-100.html",
      "timestamp": "2026-04-23T17:55:50+00:00",
      "id": "350ab7b1206c"
    },
    {
      "source": "ZDFheute Liveblog",
      "title": "Lage bei Buckelwal vor Poel zunächst unverändert",
      "url": "https://www.zdfheute.de/panorama/wal-timmy-ostsee-liveblog-100.html",
      "timestamp": "2026-04-23T17:55:50+00:00",
      "id": "d6612f34e12e"
    },
    {
      "source": "ZDFheute Liveblog",
      "title": "\"Er war nicht so aktiv\" - Buckelwal liegt noch in Bucht",
      "url": "https://www.zdfheute.de/panorama/wal-timmy-ostsee-liveblog-100.html",
      "timestamp": "2026-04-23T17:55:50+00:00",
      "id": "26ae5503dfa7"
    },
    {
      "source": "ZDFheute Liveblog",
      "title": "Wal liegt weiterhin im Wasser vor Poel",
      "url": "https://www.zdfheute.de/panorama/wal-timmy-ostsee-liveblog-100.html",
      "timestamp": "2026-04-23T17:55:50+00:00",
      "id": "381f101d4d60"
    },
    {
      "source": "ZDFheute Liveblog",
      "title": "Backhaus: Netz im Wal-Maul nicht aus Mecklenburg-Vorpommern",
      "url": "https://www.zdfheute.de/panorama/wal-timmy-ostsee-liveblog-100.html",
      "timestamp": "2026-04-23T17:55:50+00:00",
      "id": "9ce66d7d6c6e"
    },
    {
      "source": "ZDFheute Liveblog",
      "title": "Keine Details zu neuem Plan für Walrettungsinitiative",
      "url": "https://www.zdfheute.de/panorama/wal-timmy-ostsee-liveblog-100.html",
      "timestamp": "2026-04-23T17:55:50+00:00",
      "id": "51cd7ab34e3b"
    },
    {
      "source": "ZDFheute Liveblog",
      "title": "Backhaus: Ursprüngliches Rettungskonzept \"nicht mehr aktuell\"",
      "url": "https://www.zdfheute.de/panorama/wal-timmy-ostsee-liveblog-100.html",
      "timestamp": "2026-04-23T17:55:50+00:00",
      "id": "7c6373c05bd2"
    },
    {
      "source": "ZDFheute Liveblog",
      "title": "Minister: \"Wir dulden diesen Rettungsversuch\"",
      "url": "https://www.zdfheute.de/panorama/wal-timmy-ostsee-liveblog-100.html",
      "timestamp": "2026-04-23T17:55:50+00:00",
      "id": "714f9c00f98c"
    },
    {
      "source": "ZDFheute Liveblog",
      "title": "Umweltminister schreibt Wal weltweite Symbolkraft zu",
      "url": "https://www.zdfheute.de/panorama/wal-timmy-ostsee-liveblog-100.html",
      "timestamp": "2026-04-23T17:55:50+00:00",
      "id": "f82828bb3ab9"
    },
    {
      "source": "ZDFheute Liveblog",
      "title": "Backhaus: Wal ist aufmerksam, aber \"kranker Patient\"",
      "url": "https://www.zdfheute.de/panorama/wal-timmy-ostsee-liveblog-100.html",
      "timestamp": "2026-04-23T17:55:50+00:00",
      "id": "2e3aece7cd18"
    }
  ]
}